[
  {
    "Model": "H100 SXM",
    "Shaders Max boost clock (MHz)": "1500",
    "Memory Bus type": "HBM3",
    "Memory Bus Width (bit)": "5120",
    "Memory (GB)": "80",
    "Memory Clock (MT/s)": "1500",
    "Memory Bandwidth (GB/s)": "3352",
    "Half precision Processing Power (GFLOPS)": "1979000",
    "Single precision Processing Power (GFLOPS)": "989000",
    "Double precision Processing Power (GFLOPS)": "67000",
    "CUDA Compatibility": "9",
    "Thermal Design Power (watts)": "700",
    "Form Factor": "SXM card",
    "Deprecated": ""
  },
  {
    "Model": "H100",
    "Shaders Max boost clock (MHz)": "1000",
    "Memory Bus type": "HBM2e",
    "Memory Bus Width (bit)": "5120",
    "Memory (GB)": "80",
    "Memory Clock (MT/s)": "1000",
    "Memory Bandwidth (GB/s)": "2039",
    "Half precision Processing Power (GFLOPS)": "1513000",
    "Single precision Processing Power (GFLOPS)": "756000",
    "Double precision Processing Power (GFLOPS)": "51000",
    "CUDA Compatibility": "9",
    "Thermal Design Power (watts)": "350",
    "Form Factor": "PCIe card (dual-slot)",
    "Deprecated": ""
  },
  {
    "Model": "A100 80 NVLINK",
    "Shaders Max boost clock (MHz)": "1410",
    "Memory Bus type": "HBM2",
    "Memory Bus Width (bit)": "5120",
    "Memory (GB)": "80",
    "Memory Clock (MT/s)": "1215",
    "Memory Bandwidth (GB/s)": "2039",
    "Half precision Processing Power (GFLOPS)": "624000",
    "Single precision Processing Power (GFLOPS)": "312000",
    "Double precision Processing Power (GFLOPS)": "19500",
    "CUDA Compatibility": "8",
    "Thermal Design Power (watts)": "250",
    "Form Factor": "SXM",
    "Deprecated": ""
  },
  {
    "Model": "A100 40 NVLINK",
    "Shaders Max boost clock (MHz)": "1410",
    "Memory Bus type": "HBM2",
    "Memory Bus Width (bit)": "5120",
    "Memory (GB)": "40",
    "Memory Clock (MT/s)": "1215",
    "Memory Bandwidth (GB/s)": "1555",
    "Half precision Processing Power (GFLOPS)": "624000",
    "Single precision Processing Power (GFLOPS)": "312000",
    "Double precision Processing Power (GFLOPS)": "19500",
    "CUDA Compatibility": "8",
    "Thermal Design Power (watts)": "250",
    "Form Factor": "SXM",
    "Deprecated": ""
  },
  {
    "Model": "A100 80",
    "Shaders Max boost clock (MHz)": "1410",
    "Memory Bus type": "HBM2",
    "Memory Bus Width (bit)": "5120",
    "Memory (GB)": "80",
    "Memory Clock (MT/s)": "1215",
    "Memory Bandwidth (GB/s)": "1935",
    "Half precision Processing Power (GFLOPS)": "624000",
    "Single precision Processing Power (GFLOPS)": "312000",
    "Double precision Processing Power (GFLOPS)": "19500",
    "CUDA Compatibility": "8",
    "Thermal Design Power (watts)": "250",
    "Form Factor": "PCIe card (dual-slot)",
    "Deprecated": ""
  },
  {
    "Model": "A100 40",
    "Shaders Max boost clock (MHz)": "1410",
    "Memory Bus type": "HBM2",
    "Memory Bus Width (bit)": "5120",
    "Memory (GB)": "40",
    "Memory Clock (MT/s)": "1215",
    "Memory Bandwidth (GB/s)": "1555",
    "Half precision Processing Power (GFLOPS)": "624000",
    "Single precision Processing Power (GFLOPS)": "312000",
    "Double precision Processing Power (GFLOPS)": "19500",
    "CUDA Compatibility": "8",
    "Thermal Design Power (watts)": "250",
    "Form Factor": "PCIe card (dual-slot)",
    "Deprecated": ""
  },
  {
    "Model": "A30",
    "Shaders Max boost clock (MHz)": "1440",
    "Memory Bus type": "HBM2",
    "Memory Bus Width (bit)": "3072",
    "Memory (GB)": "24",
    "Memory Clock (MT/s)": "1215",
    "Memory Bandwidth (GB/s)": "933",
    "Half precision Processing Power (GFLOPS)": "330000",
    "Single precision Processing Power (GFLOPS)": "164000",
    "Double precision Processing Power (GFLOPS)": "10300",
    "CUDA Compatibility": "8",
    "Thermal Design Power (watts)": "165",
    "Form Factor": "PCIe card (dual-slot)",
    "Deprecated": ""
  },
  {
    "Model": "V100 32 NVLINK",
    "Shaders Max boost clock (MHz)": "1455",
    "Memory Bus type": "HBM2",
    "Memory Bus Width (bit)": "4096",
    "Memory (GB)": "32",
    "Memory Clock (MT/s)": "1750",
    "Memory Bandwidth (GB/s)": "900",
    "Half precision Processing Power (GFLOPS)": "125000",
    "Single precision Processing Power (GFLOPS)": "15700",
    "Double precision Processing Power (GFLOPS)": "7800",
    "CUDA Compatibility": "7",
    "Thermal Design Power (watts)": "350",
    "Form Factor": "SXM card",
    "Deprecated": ""
  },
  {
    "Model": "V100 16 NVLINK",
    "Shaders Max boost clock (MHz)": "1455",
    "Memory Bus type": "HBM2",
    "Memory Bus Width (bit)": "4096",
    "Memory (GB)": "16",
    "Memory Clock (MT/s)": "1750",
    "Memory Bandwidth (GB/s)": "900",
    "Half precision Processing Power (GFLOPS)": "125000",
    "Single precision Processing Power (GFLOPS)": "15700",
    "Double precision Processing Power (GFLOPS)": "7800",
    "CUDA Compatibility": "7",
    "Thermal Design Power (watts)": "300",
    "Form Factor": "SXM card",
    "Deprecated": ""
  },
  {
    "Model": "V100 32",
    "Shaders Max boost clock (MHz)": "1370",
    "Memory Bus type": "HBM2",
    "Memory Bus Width (bit)": "4096",
    "Memory (GB)": "32",
    "Memory Clock (MT/s)": "1750",
    "Memory Bandwidth (GB/s)": "900",
    "Half precision Processing Power (GFLOPS)": "112000",
    "Single precision Processing Power (GFLOPS)": "14000",
    "Double precision Processing Power (GFLOPS)": "7000",
    "CUDA Compatibility": "7",
    "Thermal Design Power (watts)": "250",
    "Form Factor": "PCIe card",
    "Deprecated": ""
  },
  {
    "Model": "V100 16",
    "Shaders Max boost clock (MHz)": "1370",
    "Memory Bus type": "HBM2",
    "Memory Bus Width (bit)": "4096",
    "Memory (GB)": "16",
    "Memory Clock (MT/s)": "1750",
    "Memory Bandwidth (GB/s)": "900",
    "Half precision Processing Power (GFLOPS)": "112000",
    "Single precision Processing Power (GFLOPS)": "14000",
    "Double precision Processing Power (GFLOPS)": "7000",
    "CUDA Compatibility": "7",
    "Thermal Design Power (watts)": "250",
    "Form Factor": "PCIe card",
    "Deprecated": ""
  },
  {
    "Model": "V100 FHHL",
    "Shaders Max boost clock (MHz)": "1290",
    "Memory Bus type": "HBM2",
    "Memory Bus Width (bit)": "4096",
    "Memory (GB)": "16",
    "Memory Clock (MT/s)": "1620",
    "Memory Bandwidth (GB/s)": "829",
    "Half precision Processing Power (GFLOPS)": "112000",
    "Single precision Processing Power (GFLOPS)": "14000",
    "Double precision Processing Power (GFLOPS)": "7000",
    "CUDA Compatibility": "7",
    "Thermal Design Power (watts)": "250",
    "Form Factor": "PCIe FHHL card",
    "Deprecated": ""
  },
  {
    "Model": "V100s",
    "Shaders Max boost clock (MHz)": "1370",
    "Memory Bus type": "HBM2",
    "Memory Bus Width (bit)": "4096",
    "Memory (GB)": "32",
    "Memory Clock (MT/s)": "1620",
    "Memory Bandwidth (GB/s)": "1134",
    "Half precision Processing Power (GFLOPS)": "130000",
    "Single precision Processing Power (GFLOPS)": "16400",
    "Double precision Processing Power (GFLOPS)": "8200",
    "CUDA Compatibility": "7",
    "Thermal Design Power (watts)": "250",
    "Form Factor": "PCIe card",
    "Deprecated": ""
  },
  {
    "Model": "L40",
    "Shaders Max boost clock (MHz)": "2490",
    "Memory Bus type": "GDDR6",
    "Memory Bus Width (bit)": "384",
    "Memory (GB)": "48",
    "Memory Clock (MT/s)": "2250",
    "Memory Bandwidth (GB/s)": "864",
    "Half precision Processing Power (GFLOPS)": "362100",
    "Single precision Processing Power (GFLOPS)": "181000",
    "Double precision Processing Power (GFLOPS)": "",
    "CUDA Compatibility": "8.9",
    "Thermal Design Power (watts)": "300",
    "Form Factor": "PCIe card (dual-slot)",
    "Deprecated": ""
  },
  {
    "Model": "L40S",
    "Shaders Max boost clock (MHz)": "2490",
    "Memory Bus type": "GDDR6",
    "Memory Bus Width (bit)": "384",
    "Memory (GB)": "48",
    "Memory Clock (MT/s)": "2250",
    "Memory Bandwidth (GB/s)": "864",
    "Half precision Processing Power (GFLOPS)": "733000",
    "Single precision Processing Power (GFLOPS)": "366000",
    "Double precision Processing Power (GFLOPS)": "",
    "CUDA Compatibility": "8.9",
    "Thermal Design Power (watts)": "300",
    "Form Factor": "PCIe card (dual-slot)",
    "Deprecated": ""
  },
  {
    "Model": "P100 SXM",
    "Shaders Max boost clock (MHz)": "1480",
    "Memory Bus type": "HBM2",
    "Memory Bus Width (bit)": "4096",
    "Memory (GB)": "16",
    "Memory Clock (MT/s)": "1430",
    "Memory Bandwidth (GB/s)": "732",
    "Half precision Processing Power (GFLOPS)": "21200",
    "Single precision Processing Power (GFLOPS)": "10600",
    "Double precision Processing Power (GFLOPS)": "5300",
    "CUDA Compatibility": "6",
    "Thermal Design Power (watts)": "300",
    "Form Factor": "SXM card",
    "Deprecated": ""
  },
  {
    "Model": "P100 16",
    "Shaders Max boost clock (MHz)": "1303",
    "Memory Bus type": "HBM2",
    "Memory Bus Width (bit)": "4096",
    "Memory (GB)": "16",
    "Memory Clock (MT/s)": "1430",
    "Memory Bandwidth (GB/s)": "732",
    "Half precision Processing Power (GFLOPS)": "18700",
    "Single precision Processing Power (GFLOPS)": "9300",
    "Double precision Processing Power (GFLOPS)": "4700",
    "CUDA Compatibility": "6",
    "Thermal Design Power (watts)": "250",
    "Form Factor": "PCIe card",
    "Deprecated": ""
  },
  {
    "Model": "P100 12",
    "Shaders Max boost clock (MHz)": "1303",
    "Memory Bus type": "HBM2",
    "Memory Bus Width (bit)": "3072",
    "Memory (GB)": "12",
    "Memory Clock (MT/s)": "1430",
    "Memory Bandwidth (GB/s)": "549",
    "Half precision Processing Power (GFLOPS)": "18700",
    "Single precision Processing Power (GFLOPS)": "9300",
    "Double precision Processing Power (GFLOPS)": "4700",
    "CUDA Compatibility": "6",
    "Thermal Design Power (watts)": "250",
    "Form Factor": "PCIe card",
    "Deprecated": ""
  },
  {
    "Model": "A40",
    "Shaders Max boost clock (MHz)": "1740",
    "Memory Bus type": "GDDR6",
    "Memory Bus Width (bit)": "384",
    "Memory (GB)": "48",
    "Memory Clock (MT/s)": "7248",
    "Memory Bandwidth (GB/s)": "695",
    "Half precision Processing Power (GFLOPS)": "299400",
    "Single precision Processing Power (GFLOPS)": "149600",
    "Double precision Processing Power (GFLOPS)": "",
    "CUDA Compatibility": "8.6",
    "Thermal Design Power (watts)": "300",
    "Form Factor": "PCIe card (dual-slot)",
    "Deprecated": ""
  },
  {
    "Model": "A10G",
    "Shaders Max boost clock (MHz)": "1695",
    "Memory Bus type": "GDDR6",
    "Memory Bus Width (bit)": "384",
    "Memory (GB)": "24",
    "Memory Clock (MT/s)": "6252",
    "Memory Bandwidth (GB/s)": "600",
    "Half precision Processing Power (GFLOPS)": "250000",
    "Single precision Processing Power (GFLOPS)": "125000",
    "Double precision Processing Power (GFLOPS)": "",
    "CUDA Compatibility": "8.6",
    "Thermal Design Power (watts)": "150",
    "Form Factor": "PCIe card (single-slot)",
    "Deprecated": ""
  },
  {
    "Model": "A10",
    "Shaders Max boost clock (MHz)": "1695",
    "Memory Bus type": "GDDR6",
    "Memory Bus Width (bit)": "384",
    "Memory (GB)": "24",
    "Memory Clock (MT/s)": "6252",
    "Memory Bandwidth (GB/s)": "600",
    "Half precision Processing Power (GFLOPS)": "250000",
    "Single precision Processing Power (GFLOPS)": "125000",
    "Double precision Processing Power (GFLOPS)": "",
    "CUDA Compatibility": "8.6",
    "Thermal Design Power (watts)": "150",
    "Form Factor": "PCIe card (single-slot)",
    "Deprecated": ""
  },
  {
    "Model": "K80",
    "Shaders Max boost clock (MHz)": "875",
    "Memory Bus type": "GDDR5",
    "Memory Bus Width (bit)": "768",
    "Memory (GB)": "24",
    "Memory Clock (MT/s)": "5000",
    "Memory Bandwidth (GB/s)": "480",
    "Half precision Processing Power (GFLOPS)": "4370",
    "Single precision Processing Power (GFLOPS)": "4370",
    "Double precision Processing Power (GFLOPS)": "1460",
    "CUDA Compatibility": "3.7",
    "Thermal Design Power (watts)": "300",
    "Form Factor": "Internal PCIe GPU (full-height, dual-slot)",
    "Deprecated": ""
  },
  {
    "Model": "P40",
    "Shaders Max boost clock (MHz)": "1531",
    "Memory Bus type": "GDDR5",
    "Memory Bus Width (bit)": "384",
    "Memory (GB)": "24",
    "Memory Clock (MT/s)": "7200",
    "Memory Bandwidth (GB/s)": "345",
    "Half precision Processing Power (GFLOPS)": "11758",
    "Single precision Processing Power (GFLOPS)": "11758",
    "Double precision Processing Power (GFLOPS)": "367",
    "CUDA Compatibility": "6.1",
    "Thermal Design Power (watts)": "250",
    "Form Factor": "PCIe card",
    "Deprecated": ""
  },
  {
    "Model": "T4",
    "Shaders Max boost clock (MHz)": "1590",
    "Memory Bus type": "GDDR6",
    "Memory Bus Width (bit)": "256",
    "Memory (GB)": "16",
    "Memory Clock (MT/s)": "5000",
    "Memory Bandwidth (GB/s)": "320",
    "Half precision Processing Power (GFLOPS)": "65000",
    "Single precision Processing Power (GFLOPS)": "8100",
    "Double precision Processing Power (GFLOPS)": "250",
    "CUDA Compatibility": "7.5",
    "Thermal Design Power (watts)": "70",
    "Form Factor": "PCIe card",
    "Deprecated": ""
  },
  {
    "Model": "M60",
    "Shaders Max boost clock (MHz)": "1178",
    "Memory Bus type": "GDDR5",
    "Memory Bus Width (bit)": "512",
    "Memory (GB)": "16",
    "Memory Clock (MT/s)": "5000",
    "Memory Bandwidth (GB/s)": "320",
    "Half precision Processing Power (GFLOPS)": "9650",
    "Single precision Processing Power (GFLOPS)": "9650",
    "Double precision Processing Power (GFLOPS)": "301",
    "CUDA Compatibility": "5.2",
    "Thermal Design Power (watts)": "300",
    "Form Factor": "Internal PCIe GPU (full-height, dual-slot)",
    "Deprecated": ""
  },
  {
    "Model": "K10",
    "Shaders Max boost clock (MHz)": "1178",
    "Memory Bus type": "GDDR5",
    "Memory Bus Width (bit)": "512",
    "Memory (GB)": "8",
    "Memory Clock (MT/s)": "5000",
    "Memory Bandwidth (GB/s)": "320",
    "Half precision Processing Power (GFLOPS)": "4577",
    "Single precision Processing Power (GFLOPS)": "4577",
    "Double precision Processing Power (GFLOPS)": "190",
    "CUDA Compatibility": "3",
    "Thermal Design Power (watts)": "225",
    "Form Factor": "Internal PCIe GPU (full-height, dual-slot)",
    "Deprecated": ""
  },
  {
    "Model": "L4",
    "Shaders Max boost clock (MHz)": "2040",
    "Memory Bus type": "GDDR6",
    "Memory Bus Width (bit)": "192",
    "Memory (GB)": "24",
    "Memory Clock (MT/s)": "1563",
    "Memory Bandwidth (GB/s)": "300",
    "Half precision Processing Power (GFLOPS)": "242000",
    "Single precision Processing Power (GFLOPS)": "120000",
    "Double precision Processing Power (GFLOPS)": "",
    "CUDA Compatibility": "8.9",
    "Thermal Design Power (watts)": "72",
    "Form Factor": "HHHL single slot PCIe card",
    "Deprecated": ""
  },
  {
    "Model": "A2",
    "Shaders Max boost clock (MHz)": "1770",
    "Memory Bus type": "GDDR6",
    "Memory Bus Width (bit)": "128",
    "Memory (GB)": "16",
    "Memory Clock (MT/s)": "6252",
    "Memory Bandwidth (GB/s)": "200",
    "Half precision Processing Power (GFLOPS)": "36000",
    "Single precision Processing Power (GFLOPS)": "18000",
    "Double precision Processing Power (GFLOPS)": "",
    "CUDA Compatibility": "8.6",
    "Thermal Design Power (watts)": "60",
    "Form Factor": "PCIe card (half height, single-slot)",
    "Deprecated": ""
  },
  {
    "Model": "P6",
    "Shaders Max boost clock (MHz)": "1506",
    "Memory Bus type": "GDDR5",
    "Memory Bus Width (bit)": "256",
    "Memory (GB)": "16",
    "Memory Clock (MT/s)": "3003",
    "Memory Bandwidth (GB/s)": "192",
    "Half precision Processing Power (GFLOPS)": "6169",
    "Single precision Processing Power (GFLOPS)": "6169",
    "Double precision Processing Power (GFLOPS)": "192",
    "CUDA Compatibility": "6.1",
    "Thermal Design Power (watts)": "90",
    "Form Factor": "MXM card",
    "Deprecated": ""
  },
  {
    "Model": "P4",
    "Shaders Max boost clock (MHz)": "1063",
    "Memory Bus type": "GDDR5",
    "Memory Bus Width (bit)": "256",
    "Memory (GB)": "8",
    "Memory Clock (MT/s)": "6000",
    "Memory Bandwidth (GB/s)": "192",
    "Half precision Processing Power (GFLOPS)": "5500",
    "Single precision Processing Power (GFLOPS)": "5500",
    "Double precision Processing Power (GFLOPS)": "200",
    "CUDA Compatibility": "6.1",
    "Thermal Design Power (watts)": "75",
    "Form Factor": "PCIe card",
    "Deprecated": ""
  },
  {
    "Model": "A16",
    "Shaders Max boost clock (MHz)": "1695",
    "Memory Bus type": "GDDR6",
    "Memory Bus Width (bit)": "512",
    "Memory (GB)": "64",
    "Memory Clock (MT/s)": "7242",
    "Memory Bandwidth (GB/s)": "800",
    "Half precision Processing Power (GFLOPS)": "73728",
    "Single precision Processing Power (GFLOPS)": "18432",
    "Double precision Processing Power (GFLOPS)": "1084",
    "CUDA Compatibility": "8.6",
    "Thermal Design Power (watts)": "250",
    "Form Factor": "PCIe card (dual-slot)",
    "Deprecated": ""
  },
  {
    "Model": "Quadro RTX 4000",
    "Shaders Max boost clock (MHz)": "1545",
    "Memory Bus type": "GDDR6",
    "Memory Bus Width (bit)": "256",
    "Memory (GB)": "8",
    "Memory Clock (MT/s)": "1545",
    "Memory Bandwidth (GB/s)": "416",
    "Half precision Processing Power (GFLOPS)": "14240",
    "Single precision Processing Power (GFLOPS)": "7119",
    "Double precision Processing Power (GFLOPS)": "222",
    "CUDA Compatibility": "7.5",
    "Thermal Design Power (watts)": "125",
    "Form Factor": "PCIe",
    "Deprecated": ""
  },
  {
    "Model": "Quadro RTX 5000",
    "Shaders Max boost clock (MHz)": "1815",
    "Memory Bus type": "GDDR6",
    "Memory Bus Width (bit)": "256",
    "Memory (GB)": "16",
    "Memory Clock (MT/s)": "1815",
    "Memory Bandwidth (GB/s)": "448",
    "Half precision Processing Power (GFLOPS)": "22300",
    "Single precision Processing Power (GFLOPS)": "11151",
    "Double precision Processing Power (GFLOPS)": "348",
    "CUDA Compatibility": "7.5",
    "Thermal Design Power (watts)": "230",
    "Form Factor": "PCIe",
    "Deprecated": ""
  },
  {
    "Model": "Quadro RTX 6000",
    "Shaders Max boost clock (MHz)": "1770",
    "Memory Bus type": "GDDR6",
    "Memory Bus Width (bit)": "384",
    "Memory (GB)": "24",
    "Memory Clock (MT/s)": "1770",
    "Memory Bandwidth (GB/s)": "672",
    "Half precision Processing Power (GFLOPS)": "32600",
    "Single precision Processing Power (GFLOPS)": "16312",
    "Double precision Processing Power (GFLOPS)": "509",
    "CUDA Compatibility": "7.5",
    "Thermal Design Power (watts)": "260",
    "Form Factor": "PCIe",
    "Deprecated": ""
  },
  {
    "Model": "RTX A4000",
    "Shaders Max boost clock (MHz)": "1650",
    "Memory Bus type": "GDDR6",
    "Memory Bus Width (bit)": "320",
    "Memory (GB)": "20",
    "Memory Clock (MT/s)": "1650",
    "Memory Bandwidth (GB/s)": "640",
    "Half precision Processing Power (GFLOPS)": "153400",
    "Single precision Processing Power (GFLOPS)": "19200",
    "Double precision Processing Power (GFLOPS)": "",
    "CUDA Compatibility": "8.6",
    "Thermal Design Power (watts)": "200",
    "Form Factor": "PCIe",
    "Deprecated": ""
  },
  {
    "Model": "RTX A4500",
    "Shaders Max boost clock (MHz)": "1650",
    "Memory Bus type": "GDDR6",
    "Memory Bus Width (bit)": "320",
    "Memory (GB)": "20",
    "Memory Clock (MT/s)": "1650",
    "Memory Bandwidth (GB/s)": "640",
    "Half precision Processing Power (GFLOPS)": "189200",
    "Single precision Processing Power (GFLOPS)": "23700",
    "Double precision Processing Power (GFLOPS)": "",
    "CUDA Compatibility": "8.6",
    "Thermal Design Power (watts)": "200",
    "Form Factor": "PCIe",
    "Deprecated": ""
  },
  {
    "Model": "RTX A5000",
    "Shaders Max boost clock (MHz)": "1695",
    "Memory Bus type": "GDDR6",
    "Memory Bus Width (bit)": "384",
    "Memory (GB)": "24",
    "Memory Clock (MT/s)": "1695",
    "Memory Bandwidth (GB/s)": "768",
    "Half precision Processing Power (GFLOPS)": "222200",
    "Single precision Processing Power (GFLOPS)": "27800",
    "Double precision Processing Power (GFLOPS)": "",
    "CUDA Compatibility": "8.6",
    "Thermal Design Power (watts)": "230",
    "Form Factor": "PCIe",
    "Deprecated": ""
  },
  {
    "Model": "RTX A6000",
    "Shaders Max boost clock (MHz)": "1800",
    "Memory Bus type": "GDDR6",
    "Memory Bus Width (bit)": "384",
    "Memory (GB)": "48",
    "Memory Clock (MT/s)": "1800",
    "Memory Bandwidth (GB/s)": "768",
    "Half precision Processing Power (GFLOPS)": "309700",
    "Single precision Processing Power (GFLOPS)": "38700",
    "Double precision Processing Power (GFLOPS)": "",
    "CUDA Compatibility": "8.6",
    "Thermal Design Power (watts)": "300",
    "Form Factor": "PCIe",
    "Deprecated": ""
  },
  {
    "Model": "RTX 6000 Ada",
    "Shaders Max boost clock (MHz)": "2505",
    "Memory Bus type": "GDDR6",
    "Memory Bus Width (bit)": "384",
    "Memory (GB)": "48",
    "Memory Clock (MT/s)": "2505",
    "Memory Bandwidth (GB/s)": "960",
    "Half precision Processing Power (GFLOPS)": "728500",
    "Single precision Processing Power (GFLOPS)": "91100",
    "Double precision Processing Power (GFLOPS)": "",
    "CUDA Compatibility": "8.9",
    "Thermal Design Power (watts)": "300",
    "Form Factor": "PCIe",
    "Deprecated": ""
  },
  {
    "Model": "RTX 3070",
    "Shaders Max boost clock (MHz)": "1725",
    "Memory Bus type": "GDDR6",
    "Memory Bus Width (bit)": "256",
    "Memory (GB)": "8",
    "Memory Clock (MT/s)": "1725",
    "Memory Bandwidth (GB/s)": "448",
    "Half precision Processing Power (GFLOPS)": "20310",
    "Single precision Processing Power (GFLOPS)": "20310",
    "Double precision Processing Power (GFLOPS)": "318",
    "CUDA Compatibility": "8.6",
    "Thermal Design Power (watts)": "220",
    "Form Factor": "PCIe",
    "Deprecated": ""
  },
  {
    "Model": "RTX 3070",
    "Shaders Max boost clock (MHz)": "1770",
    "Memory Bus type": "GDDR6",
    "Memory Bus Width (bit)": "256",
    "Memory (GB)": "8",
    "Memory Clock (MT/s)": "1770",
    "Memory Bandwidth (GB/s)": "608",
    "Half precision Processing Power (GFLOPS)": "21750",
    "Single precision Processing Power (GFLOPS)": "21750",
    "Double precision Processing Power (GFLOPS)": "340",
    "CUDA Compatibility": "8.6",
    "Thermal Design Power (watts)": "290",
    "Form Factor": "PCIe",
    "Deprecated": ""
  },
  {
    "Model": "RTX 3080",
    "Shaders Max boost clock (MHz)": "1710",
    "Memory Bus type": "GDDR6",
    "Memory Bus Width (bit)": "384",
    "Memory (GB)": "12",
    "Memory Clock (MT/s)": "1710",
    "Memory Bandwidth (GB/s)": "912",
    "Half precision Processing Power (GFLOPS)": "29770",
    "Single precision Processing Power (GFLOPS)": "29770",
    "Double precision Processing Power (GFLOPS)": "465",
    "CUDA Compatibility": "8.6",
    "Thermal Design Power (watts)": "350",
    "Form Factor": "PCIe",
    "Deprecated": ""
  },
  {
    "Model": "RTX 3080 Ti",
    "Shaders Max boost clock (MHz)": "1665",
    "Memory Bus type": "GDDR6",
    "Memory Bus Width (bit)": "384",
    "Memory (GB)": "12",
    "Memory Clock (MT/s)": "1665",
    "Memory Bandwidth (GB/s)": "912",
    "Half precision Processing Power (GFLOPS)": "34100",
    "Single precision Processing Power (GFLOPS)": "34100",
    "Double precision Processing Power (GFLOPS)": "533",
    "CUDA Compatibility": "8.6",
    "Thermal Design Power (watts)": "350",
    "Form Factor": "PCIe",
    "Deprecated": ""
  },
  {
    "Model": "RTX 3090",
    "Shaders Max boost clock (MHz)": "1695",
    "Memory Bus type": "GDDR6",
    "Memory Bus Width (bit)": "384",
    "Memory (GB)": "24",
    "Memory Clock (MT/s)": "1695",
    "Memory Bandwidth (GB/s)": "935",
    "Half precision Processing Power (GFLOPS)": "35580",
    "Single precision Processing Power (GFLOPS)": "35580",
    "Double precision Processing Power (GFLOPS)": "558",
    "CUDA Compatibility": "8.6",
    "Thermal Design Power (watts)": "350",
    "Form Factor": "PCIe",
    "Deprecated": ""
  },
  {
    "Model": "RTX 3090 Ti",
    "Shaders Max boost clock (MHz)": "1860",
    "Memory Bus type": "GDDR6",
    "Memory Bus Width (bit)": "384",
    "Memory (GB)": "24",
    "Memory Clock (MT/s)": "1860",
    "Memory Bandwidth (GB/s)": "1008",
    "Half precision Processing Power (GFLOPS)": "40000",
    "Single precision Processing Power (GFLOPS)": "40000",
    "Double precision Processing Power (GFLOPS)": "625",
    "CUDA Compatibility": "8.6",
    "Thermal Design Power (watts)": "450",
    "Form Factor": "PCIe",
    "Deprecated": ""
  },
  {
    "Model": "RTX 4070 Ti",
    "Shaders Max boost clock (MHz)": "2475",
    "Memory Bus type": "GDDR6",
    "Memory Bus Width (bit)": "158",
    "Memory (GB)": "12",
    "Memory Clock (MT/s)": "2475",
    "Memory Bandwidth (GB/s)": "504",
    "Half precision Processing Power (GFLOPS)": "29100",
    "Single precision Processing Power (GFLOPS)": "29100",
    "Double precision Processing Power (GFLOPS)": "455",
    "CUDA Compatibility": "8.9",
    "Thermal Design Power (watts)": "200",
    "Form Factor": "PCIe",
    "Deprecated": ""
  },
  {
    "Model": "RTX 4070 Ti",
    "Shaders Max boost clock (MHz)": "2610",
    "Memory Bus type": "GDDR6",
    "Memory Bus Width (bit)": "208",
    "Memory (GB)": "12",
    "Memory Clock (MT/s)": "2610",
    "Memory Bandwidth (GB/s)": "504",
    "Half precision Processing Power (GFLOPS)": "40100",
    "Single precision Processing Power (GFLOPS)": "40100",
    "Double precision Processing Power (GFLOPS)": "627",
    "CUDA Compatibility": "8.9",
    "Thermal Design Power (watts)": "285",
    "Form Factor": "PCIe",
    "Deprecated": ""
  },
  {
    "Model": "RTX 4080",
    "Shaders Max boost clock (MHz)": "2505",
    "Memory Bus type": "GDDR6",
    "Memory Bus Width (bit)": "280",
    "Memory (GB)": "16",
    "Memory Clock (MT/s)": "2505",
    "Memory Bandwidth (GB/s)": "717",
    "Half precision Processing Power (GFLOPS)": "48800",
    "Single precision Processing Power (GFLOPS)": "48800",
    "Double precision Processing Power (GFLOPS)": "761",
    "CUDA Compatibility": "8.9",
    "Thermal Design Power (watts)": "320",
    "Form Factor": "PCIe",
    "Deprecated": ""
  },
  {
    "Model": "RTX 4090",
    "Shaders Max boost clock (MHz)": "2520",
    "Memory Bus type": "GDDR6",
    "Memory Bus Width (bit)": "443",
    "Memory (GB)": "24",
    "Memory Clock (MT/s)": "2520",
    "Memory Bandwidth (GB/s)": "1008",
    "Half precision Processing Power (GFLOPS)": "82600",
    "Single precision Processing Power (GFLOPS)": "82600",
    "Double precision Processing Power (GFLOPS)": "1291",
    "CUDA Compatibility": "8.9",
    "Thermal Design Power (watts)": "450",
    "Form Factor": "PCIe",
    "Deprecated": ""
  },
  {
    "Model": "M10",
    "Shaders Max boost clock (MHz)": "?",
    "Memory Bus type": "GDDR5",
    "Memory Bus Width (bit)": "512",
    "Memory (GB)": "32",
    "Memory Clock (MT/s)": "5188",
    "Memory Bandwidth (GB/s)": "332",
    "Half precision Processing Power (GFLOPS)": "5289",
    "Single precision Processing Power (GFLOPS)": "5289",
    "Double precision Processing Power (GFLOPS)": "165",
    "CUDA Compatibility": "5.2",
    "Thermal Design Power (watts)": "225",
    "Form Factor": "Internal PCIe GPU (full-height, dual-slot)",
    "Deprecated": "true"
  },
  {
    "Model": "M40 12",
    "Shaders Max boost clock (MHz)": "1114",
    "Memory Bus type": "GDDR5",
    "Memory Bus Width (bit)": "384",
    "Memory (GB)": "12",
    "Memory Clock (MT/s)": "6000",
    "Memory Bandwidth (GB/s)": "288",
    "Half precision Processing Power (GFLOPS)": "6844",
    "Single precision Processing Power (GFLOPS)": "6844",
    "Double precision Processing Power (GFLOPS)": "213",
    "CUDA Compatibility": "5.2",
    "Thermal Design Power (watts)": "250",
    "Form Factor": "Internal PCIe GPU (full-height, dual-slot)",
    "Deprecated": "true"
  },
  {
    "Model": "M40 24",
    "Shaders Max boost clock (MHz)": "1114",
    "Memory Bus type": "GDDR5",
    "Memory Bus Width (bit)": "384",
    "Memory (GB)": "24",
    "Memory Clock (MT/s)": "6000",
    "Memory Bandwidth (GB/s)": "288",
    "Half precision Processing Power (GFLOPS)": "6844",
    "Single precision Processing Power (GFLOPS)": "6844",
    "Double precision Processing Power (GFLOPS)": "213",
    "CUDA Compatibility": "5.2",
    "Thermal Design Power (watts)": "250",
    "Form Factor": "Internal PCIe GPU (full-height, dual-slot)",
    "Deprecated": "true"
  },
  {
    "Model": "S2070",
    "Shaders Max boost clock (MHz)": "—",
    "Memory Bus type": "GDDR5",
    "Memory Bus Width (bit)": "1536",
    "Memory (GB)": "24",
    "Memory Clock (MT/s)": "3",
    "Memory Bandwidth (GB/s)": "593",
    "Half precision Processing Power (GFLOPS)": "4121",
    "Single precision Processing Power (GFLOPS)": "4121",
    "Double precision Processing Power (GFLOPS)": "2060",
    "CUDA Compatibility": "2",
    "Thermal Design Power (watts)": "900",
    "Form Factor": "1U rack-mount external GPUs, connect via 2× PCIe (×8 or ×16)",
    "Deprecated": "true"
  },
  {
    "Model": "S2050",
    "Shaders Max boost clock (MHz)": "—",
    "Memory Bus type": "GDDR5",
    "Memory Bus Width (bit)": "1536",
    "Memory (GB)": "12",
    "Memory Clock (MT/s)": "3",
    "Memory Bandwidth (GB/s)": "593",
    "Half precision Processing Power (GFLOPS)": "4121",
    "Single precision Processing Power (GFLOPS)": "4121",
    "Double precision Processing Power (GFLOPS)": "2060",
    "CUDA Compatibility": "2",
    "Thermal Design Power (watts)": "900",
    "Form Factor": "1U rack-mount external GPUs, connect via 2× PCIe (×8 or ×16)",
    "Deprecated": "true"
  },
  {
    "Model": "Quadro Plex 2200 S4",
    "Shaders Max boost clock (MHz)": "—",
    "Memory Bus type": "GDDR3",
    "Memory Bus Width (bit)": "2048",
    "Memory (GB)": "16",
    "Memory Clock (MT/s)": "1600",
    "Memory Bandwidth (GB/s)": "409",
    "Half precision Processing Power (GFLOPS)": "2488",
    "Single precision Processing Power (GFLOPS)": "2488",
    "Double precision Processing Power (GFLOPS)": "311",
    "CUDA Compatibility": "1.3",
    "Thermal Design Power (watts)": "1200",
    "Form Factor": "1U rack-mount external GPUs, connect via 2× PCIe (×8 or ×16)",
    "Deprecated": "true"
  },
  {
    "Model": "S1075",
    "Shaders Max boost clock (MHz)": "—",
    "Memory Bus type": "GDDR3",
    "Memory Bus Width (bit)": "2048",
    "Memory (GB)": "16",
    "Memory Clock (MT/s)": "1538",
    "Memory Bandwidth (GB/s)": "394",
    "Half precision Processing Power (GFLOPS)": "2764",
    "Single precision Processing Power (GFLOPS)": "2764",
    "Double precision Processing Power (GFLOPS)": "345",
    "CUDA Compatibility": "1.3",
    "Thermal Design Power (watts)": "",
    "Form Factor": "1U rack-mount external GPUs, connect via 1× PCIe (×8 or ×16)",
    "Deprecated": "true"
  },
  {
    "Model": "S1070 500",
    "Shaders Max boost clock (MHz)": "—",
    "Memory Bus type": "GDDR3",
    "Memory Bus Width (bit)": "2048",
    "Memory (GB)": "16",
    "Memory Clock (MT/s)": "1538",
    "Memory Bandwidth (GB/s)": "394",
    "Half precision Processing Power (GFLOPS)": "2764",
    "Single precision Processing Power (GFLOPS)": "2764",
    "Double precision Processing Power (GFLOPS)": "345",
    "CUDA Compatibility": "1.3",
    "Thermal Design Power (watts)": "800",
    "Form Factor": "1U rack-mount external GPUs, connect via 2× PCIe (×8 or ×16)",
    "Deprecated": "true"
  },
  {
    "Model": "S1070 400",
    "Shaders Max boost clock (MHz)": "—",
    "Memory Bus type": "GDDR3",
    "Memory Bus Width (bit)": "2048",
    "Memory (GB)": "16",
    "Memory Clock (MT/s)": "1538",
    "Memory Bandwidth (GB/s)": "394",
    "Half precision Processing Power (GFLOPS)": "2488",
    "Single precision Processing Power (GFLOPS)": "2488",
    "Double precision Processing Power (GFLOPS)": "311",
    "CUDA Compatibility": "1.3",
    "Thermal Design Power (watts)": "800",
    "Form Factor": "1U rack-mount external GPUs, connect via 2× PCIe (×8 or ×16)",
    "Deprecated": "true"
  },
  {
    "Model": "S870",
    "Shaders Max boost clock (MHz)": "—",
    "Memory Bus type": "GDDR3",
    "Memory Bus Width (bit)": "1536",
    "Memory (GB)": "6",
    "Memory Clock (MT/s)": "1600",
    "Memory Bandwidth (GB/s)": "307",
    "Half precision Processing Power (GFLOPS)": "1382",
    "Single precision Processing Power (GFLOPS)": "1382",
    "Double precision Processing Power (GFLOPS)": "",
    "CUDA Compatibility": "1",
    "Thermal Design Power (watts)": "",
    "Form Factor": "1U rack-mount external GPUs, connect via 2× PCIe (×16)",
    "Deprecated": "true"
  },
  {
    "Model": "K40",
    "Shaders Max boost clock (MHz)": "875",
    "Memory Bus type": "GDDR5",
    "Memory Bus Width (bit)": "384",
    "Memory (GB)": "12",
    "Memory Clock (MT/s)": "6000",
    "Memory Bandwidth (GB/s)": "288",
    "Half precision Processing Power (GFLOPS)": "5040",
    "Single precision Processing Power (GFLOPS)": "5040",
    "Double precision Processing Power (GFLOPS)": "1680",
    "CUDA Compatibility": "3.5",
    "Thermal Design Power (watts)": "235",
    "Form Factor": "Internal PCIe GPU (full-height, dual-slot)",
    "Deprecated": "true"
  },
  {
    "Model": "K20X",
    "Shaders Max boost clock (MHz)": "?",
    "Memory Bus type": "GDDR5",
    "Memory Bus Width (bit)": "384",
    "Memory (GB)": "6",
    "Memory Clock (MT/s)": "5200",
    "Memory Bandwidth (GB/s)": "250",
    "Half precision Processing Power (GFLOPS)": "3935",
    "Single precision Processing Power (GFLOPS)": "3935",
    "Double precision Processing Power (GFLOPS)": "1312",
    "CUDA Compatibility": "3.5",
    "Thermal Design Power (watts)": "235",
    "Form Factor": "Internal PCIe GPU (full-height, dual-slot)",
    "Deprecated": "true"
  },
  {
    "Model": "K20",
    "Shaders Max boost clock (MHz)": "758",
    "Memory Bus type": "GDDR5",
    "Memory Bus Width (bit)": "320",
    "Memory (GB)": "5",
    "Memory Clock (MT/s)": "5200",
    "Memory Bandwidth (GB/s)": "208",
    "Half precision Processing Power (GFLOPS)": "3524",
    "Single precision Processing Power (GFLOPS)": "3524",
    "Double precision Processing Power (GFLOPS)": "1175",
    "CUDA Compatibility": "3.5",
    "Thermal Design Power (watts)": "225",
    "Form Factor": "Internal PCIe GPU (full-height, dual-slot)",
    "Deprecated": "true"
  },
  {
    "Model": "Quadro Plex 2200 D2",
    "Shaders Max boost clock (MHz)": "—",
    "Memory Bus type": "GDDR3",
    "Memory Bus Width (bit)": "1024",
    "Memory (GB)": "8",
    "Memory Clock (MT/s)": "1600",
    "Memory Bandwidth (GB/s)": "204",
    "Half precision Processing Power (GFLOPS)": "1244",
    "Single precision Processing Power (GFLOPS)": "1244",
    "Double precision Processing Power (GFLOPS)": "155",
    "CUDA Compatibility": "1.3",
    "Thermal Design Power (watts)": "",
    "Form Factor": "Deskside or 3U rack-mount external GPUs with 4 dual-link DVI outputs",
    "Deprecated": "true"
  },
  {
    "Model": "M2090",
    "Shaders Max boost clock (MHz)": "—",
    "Memory Bus type": "GDDR5",
    "Memory Bus Width (bit)": "384",
    "Memory (GB)": "6",
    "Memory Clock (MT/s)": "3700",
    "Memory Bandwidth (GB/s)": "177",
    "Half precision Processing Power (GFLOPS)": "1331",
    "Single precision Processing Power (GFLOPS)": "1331",
    "Double precision Processing Power (GFLOPS)": "665",
    "CUDA Compatibility": "2",
    "Thermal Design Power (watts)": "225",
    "Form Factor": "Internal PCIe GPU (full-height, dual-slot)",
    "Deprecated": "true"
  },
  {
    "Model": "D870",
    "Shaders Max boost clock (MHz)": "—",
    "Memory Bus type": "GDDR3",
    "Memory Bus Width (bit)": "768",
    "Memory (GB)": "3",
    "Memory Clock (MT/s)": "1600",
    "Memory Bandwidth (GB/s)": "153",
    "Half precision Processing Power (GFLOPS)": "691",
    "Single precision Processing Power (GFLOPS)": "691",
    "Double precision Processing Power (GFLOPS)": "",
    "CUDA Compatibility": "1",
    "Thermal Design Power (watts)": "520",
    "Form Factor": "Deskside or 3U rack-mount external GPUs",
    "Deprecated": "true"
  },
  {
    "Model": "M2070",
    "Shaders Max boost clock (MHz)": "—",
    "Memory Bus type": "GDDR5",
    "Memory Bus Width (bit)": "384",
    "Memory (GB)": "6",
    "Memory Clock (MT/s)": "3132",
    "Memory Bandwidth (GB/s)": "150",
    "Half precision Processing Power (GFLOPS)": "1030",
    "Single precision Processing Power (GFLOPS)": "1030",
    "Double precision Processing Power (GFLOPS)": "515",
    "CUDA Compatibility": "2",
    "Thermal Design Power (watts)": "225",
    "Form Factor": "Internal PCIe GPU (full-height, dual-slot)",
    "Deprecated": "true"
  },
  {
    "Model": "M2070Q",
    "Shaders Max boost clock (MHz)": "—",
    "Memory Bus type": "GDDR5",
    "Memory Bus Width (bit)": "384",
    "Memory (GB)": "6",
    "Memory Clock (MT/s)": "3132",
    "Memory Bandwidth (GB/s)": "150",
    "Half precision Processing Power (GFLOPS)": "1030",
    "Single precision Processing Power (GFLOPS)": "1030",
    "Double precision Processing Power (GFLOPS)": "515",
    "CUDA Compatibility": "2",
    "Thermal Design Power (watts)": "225",
    "Form Factor": "Internal PCIe GPU (full-height, dual-slot)",
    "Deprecated": "true"
  },
  {
    "Model": "M2050",
    "Shaders Max boost clock (MHz)": "—",
    "Memory Bus type": "GDDR5",
    "Memory Bus Width (bit)": "384",
    "Memory (GB)": "3",
    "Memory Clock (MT/s)": "3092",
    "Memory Bandwidth (GB/s)": "148",
    "Half precision Processing Power (GFLOPS)": "1030",
    "Single precision Processing Power (GFLOPS)": "1030",
    "Double precision Processing Power (GFLOPS)": "515",
    "CUDA Compatibility": "2",
    "Thermal Design Power (watts)": "225",
    "Form Factor": "Internal PCIe GPU (full-height, dual-slot)",
    "Deprecated": "true"
  },
  {
    "Model": "M6",
    "Shaders Max boost clock (MHz)": "1051",
    "Memory Bus type": "GDDR5",
    "Memory Bus Width (bit)": "256",
    "Memory (GB)": "8",
    "Memory Clock (MT/s)": "4600",
    "Memory Bandwidth (GB/s)": "147",
    "Half precision Processing Power (GFLOPS)": "3229",
    "Single precision Processing Power (GFLOPS)": "3229",
    "Double precision Processing Power (GFLOPS)": "100",
    "CUDA Compatibility": "5.2",
    "Thermal Design Power (watts)": "100",
    "Form Factor": "Internal MXM GPU",
    "Deprecated": "true"
  },
  {
    "Model": "C2075",
    "Shaders Max boost clock (MHz)": "—",
    "Memory Bus type": "GDDR5",
    "Memory Bus Width (bit)": "384",
    "Memory (GB)": "6",
    "Memory Clock (MT/s)": "3000",
    "Memory Bandwidth (GB/s)": "144",
    "Half precision Processing Power (GFLOPS)": "1030",
    "Single precision Processing Power (GFLOPS)": "1030",
    "Double precision Processing Power (GFLOPS)": "515",
    "CUDA Compatibility": "2",
    "Thermal Design Power (watts)": "225",
    "Form Factor": "Internal PCIe GPU (full-height, dual-slot)",
    "Deprecated": "true"
  },
  {
    "Model": "C2070",
    "Shaders Max boost clock (MHz)": "—",
    "Memory Bus type": "GDDR5",
    "Memory Bus Width (bit)": "384",
    "Memory (GB)": "6",
    "Memory Clock (MT/s)": "3000",
    "Memory Bandwidth (GB/s)": "144",
    "Half precision Processing Power (GFLOPS)": "1030",
    "Single precision Processing Power (GFLOPS)": "1030",
    "Double precision Processing Power (GFLOPS)": "515",
    "CUDA Compatibility": "2",
    "Thermal Design Power (watts)": "247",
    "Form Factor": "Internal PCIe GPU (full-height, dual-slot)",
    "Deprecated": "true"
  },
  {
    "Model": "C2050",
    "Shaders Max boost clock (MHz)": "—",
    "Memory Bus type": "GDDR5",
    "Memory Bus Width (bit)": "384",
    "Memory (GB)": "3",
    "Memory Clock (MT/s)": "3000",
    "Memory Bandwidth (GB/s)": "144",
    "Half precision Processing Power (GFLOPS)": "1030",
    "Single precision Processing Power (GFLOPS)": "1030",
    "Double precision Processing Power (GFLOPS)": "515",
    "CUDA Compatibility": "2",
    "Thermal Design Power (watts)": "247",
    "Form Factor": "Internal PCIe GPU (full-height, dual-slot)",
    "Deprecated": "true"
  },
  {
    "Model": "C1060",
    "Shaders Max boost clock (MHz)": "—",
    "Memory Bus type": "GDDR3",
    "Memory Bus Width (bit)": "512",
    "Memory (GB)": "4",
    "Memory Clock (MT/s)": "1600",
    "Memory Bandwidth (GB/s)": "102",
    "Half precision Processing Power (GFLOPS)": "622",
    "Single precision Processing Power (GFLOPS)": "622",
    "Double precision Processing Power (GFLOPS)": "77",
    "CUDA Compatibility": "1.3",
    "Thermal Design Power (watts)": "187",
    "Form Factor": "Internal PCIe GPU (full-height, dual-slot)",
    "Deprecated": "true"
  },
  {
    "Model": "M4",
    "Shaders Max boost clock (MHz)": "1072",
    "Memory Bus type": "GDDR5",
    "Memory Bus Width (bit)": "128",
    "Memory (GB)": "4",
    "Memory Clock (MT/s)": "5500",
    "Memory Bandwidth (GB/s)": "88",
    "Half precision Processing Power (GFLOPS)": "2195",
    "Single precision Processing Power (GFLOPS)": "2195",
    "Double precision Processing Power (GFLOPS)": "68",
    "CUDA Compatibility": "5.2",
    "Thermal Design Power (watts)": "75",
    "Form Factor": "Internal PCIe GPU (half-height, single-slot)",
    "Deprecated": "true"
  },
  {
    "Model": "C870",
    "Shaders Max boost clock (MHz)": "—",
    "Memory Bus type": "GDDR3",
    "Memory Bus Width (bit)": "384",
    "Memory (GB)": "1.5",
    "Memory Clock (MT/s)": "1600",
    "Memory Bandwidth (GB/s)": "76",
    "Half precision Processing Power (GFLOPS)": "345",
    "Single precision Processing Power (GFLOPS)": "345",
    "Double precision Processing Power (GFLOPS)": "",
    "CUDA Compatibility": "1",
    "Thermal Design Power (watts)": "170",
    "Form Factor": "Internal PCIe GPU (full-height, dual-slot)",
    "Deprecated": "true"
  }
]
